comment_creator/__init__.py
comment_creator/comment_creator.py
comment_creator-0.0.5.data/scripts/comment_creator.py
comment_creator-0.0.5.dist-info/LICENSE
comment_creator-0.0.5.dist-info/METADATA
comment_creator-0.0.5.dist-info/WHEEL
comment_creator-0.0.5.dist-info/top_level.txt
comment_creator-0.0.5.dist-info/RECORD
