Metadata-Version: 2.1
Name: comment-creator
Version: 0.0.5
Summary: Generate big comment type print statements.
Home-page: https://github.com/divakaivan/icc-comments
Author: Ivan Ivanov
Author-email: isivanov98@outlook.com
License: UNKNOWN
Platform: UNKNOWN
Classifier: Programming Language :: Python :: 3.7
Classifier: License :: OSI Approved :: MIT License
Classifier: Operating System :: OS Independent
